Metadata-Version: 1.0
Name: MM-BiGauss
Version: 0.1
Summary: Binomial and Gaussian distributions
Home-page: UNKNOWN
Author: MM
Author-email: magy0620@yahoo.com
License: UNKNOWN
Platform: UNKNOWN
